ez_setup.py
funkcie.py
pohyb.py
rCBK2.py
robot.py
robotCezBody3.py
robotCezBody4.py
robotCezBodySum.py
robotKruh.py
robotKruhsChybou.py
setup.cfg
setup.py
zapisDoSuboru.py
M_robot.egg-info/PKG-INFO
M_robot.egg-info/SOURCES.txt
M_robot.egg-info/dependency_links.txt
M_robot.egg-info/requires.txt
M_robot.egg-info/top_level.txt