Metadata-Version: 1.0
Name: M-robot
Version: 0.39
Summary: 2-D movement robot simulation
Home-page: UNKNOWN
Author: Martin Bednar
Author-email: martin.bednar@hotmail.sk
License: UNKNOWN
Platform: UNKNOWN
